vibetest/__init__.py
vibetest/agents.py
vibetest/mcp_server.py
vibetest-0.1.2.dist-info/METADATA
vibetest-0.1.2.dist-info/WHEEL
vibetest-0.1.2.dist-info/entry_points.txt
vibetest-0.1.2.dist-info/top_level.txt
vibetest-0.1.2.dist-info/RECORD
